db/__init__.py
db/vulndb_full.json
src/__init__.py
src/headers.py
src/report.py
src/requirements.py
src/secpip.py
src/utils.py
secpip-1.0.0rc1.dist-info/LICENSE.md
secpip-1.0.0rc1.dist-info/METADATA
secpip-1.0.0rc1.dist-info/WHEEL
secpip-1.0.0rc1.dist-info/entry_points.txt
secpip-1.0.0rc1.dist-info/top_level.txt
secpip-1.0.0rc1.dist-info/RECORD
