Metadata-Version: 2.1
Name: secpip
Version: 1.0.0rc1
Summary: Secure Pip Package Management Tool
Home-page: https://github.com/myasinsaglam/secpip
Author: ['M.Yasin SAGLAM']
Author-email: myasinsaglam@crypttech.com
License: MIT
Keywords: secpip python pip security vulnerability secure package install manage dump download report migrate uninstall
Platform: UNKNOWN
Classifier: Development Status :: 4 - Beta
Classifier: Environment :: Console
Classifier: Intended Audience :: Developers
Classifier: Intended Audience :: Information Technology
Classifier: Intended Audience :: Science/Research
Classifier: Intended Audience :: System Administrators
Classifier: Programming Language :: Python :: 3
Classifier: Operating System :: OS Independent
Classifier: License :: OSI Approved :: MIT License 
Classifier: Natural Language :: English
Classifier: Topic :: Scientific/Engineering
Classifier: Topic :: Scientific/Engineering :: Artificial Intelligence
Classifier: Topic :: Scientific/Engineering :: Information Analysis
Classifier: Topic :: Security
Classifier: Topic :: Software Development
Classifier: Topic :: Text Processing
Classifier: Topic :: Utilities
Requires-Dist: packaging
Requires-Dist: pip (==20.2.4)
Requires-Dist: requests
Requires-Dist: termcolor
Requires-Dist: virtualenv
